hierarchy_utils/__init__.py
hierarchy_utils/main.py
hierarchy_utils/tests/main.py
hierarchy_utils-0.1.3.dist-info/LICENSE
hierarchy_utils-0.1.3.dist-info/WHEEL
hierarchy_utils-0.1.3.dist-info/METADATA
hierarchy_utils-0.1.3.dist-info/RECORD
