Metadata-Version: 2.1
Name: hierarchy-utils
Version: 0.1.3
Summary: Utilities for working with hierarchical data structures.
Home-page: https://github.com/joefromct/py-hierarchy-utils
License: MIT
Requires-Python: >=3.5,<4.0
Classifier: License :: OSI Approved :: MIT License
Classifier: Programming Language :: Python :: 3
Classifier: Programming Language :: Python :: 3.5
Classifier: Programming Language :: Python :: 3.6
Classifier: Programming Language :: Python :: 3.7
